[
  {
    "video_id": "oe81R6aWM0A",
    "url": "https://www.youtube.com/shorts/oe81R6aWM0A",
    "title": "Insurance Companies Must Reveal Your Wildfire Risk Score in 2026",
    "article_slug": "your-wildfire-risk-score-now-has-to-be-disclosed",
    "published_at": "2026-06-23T02:04:04.777960+00:00"
  },
  {
    "shorts_id": "dQz9RGmlhxI",
    "shorts_url": "https://www.youtube.com/shorts/dQz9RGmlhxI",
    "title": "Your Mortgage Lender's Insurance Trap (What They Won't Explain)",
    "article_slug": "mortgage-lender-insurance-requirements",
    "published_at": "2026-06-15T16:16:36.491776+00:00",
    "standard_id": "syIn1xHGmcQ",
    "standard_url": "https://www.youtube.com/watch?v=syIn1xHGmcQ"
  },
  {
    "shorts_id": "zzagShQjqys",
    "shorts_url": "https://www.youtube.com/shorts/zzagShQjqys",
    "title": "The $110K Home Insurance Gap Nobody Talks About",
    "article_slug": "what-is-dwelling-coverage-in-home-insurance",
    "published_at": "2026-06-10T21:45:08.584470+00:00",
    "standard_id": "wBwyw2M6yK8",
    "standard_url": "https://www.youtube.com/watch?v=wBwyw2M6yK8"
  },
  {
    "shorts_id": "5Fa6XDOsJOw",
    "shorts_url": "https://www.youtube.com/shorts/5Fa6XDOsJOw",
    "title": "The $110K Insurance Gap Most Homeowners Don't Know About",
    "article_slug": "what-is-dwelling-coverage-in-home-insurance",
    "published_at": "2026-06-08T14:51:29.304921+00:00",
    "standard_id": "KCogNM4bLkk",
    "standard_url": "https://www.youtube.com/watch?v=KCogNM4bLkk"
  },
  {
    "shorts_id": "SR1eMcjnRpw",
    "shorts_url": "https://www.youtube.com/shorts/SR1eMcjnRpw",
    "title": "Why Your Neighbor Pays $1,500 Less for Home Insurance",
    "article_slug": "how-much-does-homeowners-insurance-cost",
    "published_at": "2026-06-01T16:39:21.959751+00:00",
    "standard_id": "2lIbI7WUmz4",
    "standard_url": "https://www.youtube.com/watch?v=2lIbI7WUmz4"
  },
  {
    "shorts_id": "2vai5qhItTA",
    "shorts_url": "https://www.youtube.com/shorts/2vai5qhItTA",
    "title": "3 Homeowners Insurance Gaps That Cost Families Everything",
    "article_slug": "what-does-homeowners-insurance-cover",
    "published_at": "2026-05-29T01:14:40.231606+00:00",
    "standard_id": "OFSZ1VlCIJk",
    "standard_url": "https://www.youtube.com/watch?v=OFSZ1VlCIJk"
  },
  {
    "shorts_id": "KedcbR9GbS4",
    "shorts_url": "https://www.youtube.com/shorts/KedcbR9GbS4",
    "title": "3 Homeowners Insurance Gaps That Cost You Thousands",
    "article_slug": "what-does-homeowners-insurance-cover",
    "published_at": "2026-05-19T15:43:34.753343+00:00",
    "standard_id": "dckffxyS9GU",
    "standard_url": "https://www.youtube.com/watch?v=dckffxyS9GU"
  },
  {
    "shorts_id": "HP4pVHG6jOI",
    "shorts_url": "https://www.youtube.com/shorts/HP4pVHG6jOI",
    "title": "3 Homeowners Insurance Gaps That Will Shock You",
    "article_slug": "what-does-homeowners-insurance-cover",
    "published_at": "2026-05-19T14:59:39.256289+00:00",
    "standard_id": "szEBX_p9rxg",
    "standard_url": "https://www.youtube.com/watch?v=szEBX_p9rxg"
  },
  {
    "shorts_id": "NxHZpS1jBdw",
    "shorts_url": "https://www.youtube.com/shorts/NxHZpS1jBdw",
    "title": "3 Homeowners Insurance Secrets That Could Save You Thousands",
    "article_slug": "what-does-homeowners-insurance-cover",
    "published_at": "2026-05-19T04:42:46.624147+00:00",
    "standard_id": "erDDJl1JAx4",
    "standard_url": "https://www.youtube.com/watch?v=erDDJl1JAx4"
  }
]